{
  "data": [
    {
      "country": "Chile",
      "name": "Kasimir Mccall",
      "address": "827-3322 Montes, Rd."
    },
    {
      "country": "Peru",
      "name": "Harper Patterson",
      "address": "267-3203 Et Road"
    },
    {
      "country": "United Kingdom",
      "name": "Patrick Curtis",
      "address": "P.O. Box 236, 994 Molestie St."
    },
    {
      "country": "Netherlands",
      "name": "Philip Sparks",
      "address": "P.O. Box 952, 5660 Sit Road"
    },
    {
      "country": "United Kingdom",
      "name": "Hop Peters",
      "address": "P.O. Box 578, 7687 Luctus Avenue"
    },
    {
      "country": "Sweden",
      "name": "April Collins",
      "address": "Ap #457-5009 Dui, Av."
    },
    {
      "country": "New Zealand",
      "name": "Kitra Lambert",
      "address": "P.O. Box 613, 6512 Diam St."
    },
    {
      "country": "Italy",
      "name": "Kellie Roman",
      "address": "Ap #823-1953 Proin St."
    },
    {
      "country": "Austria",
      "name": "Leilani Norris",
      "address": "521-445 Adipiscing, Road"
    },
    {
      "country": "Costa Rica",
      "name": "Kimberly Castaneda",
      "address": "924-6271 Cubilia Rd."
    },
    {
      "country": "New Zealand",
      "name": "Phoebe Middleton",
      "address": "Ap #746-9081 Vitae, Ave"
    },
    {
      "country": "New Zealand",
      "name": "Mannix Barnes",
      "address": "7245 Sed Rd."
    },
    {
      "country": "Nigeria",
      "name": "Lavinia Stephens",
      "address": "Ap #279-4173 Mauris Road"
    },
    {
      "country": "Belgium",
      "name": "Wyoming Wilson",
      "address": "P.O. Box 505, 610 Lorem, Road"
    },
    {
      "country": "Italy",
      "name": "Kibo Patton",
      "address": "Ap #646-2376 Molestie Ave"
    },
    {
      "country": "United Kingdom",
      "name": "Ciara Willis",
      "address": "Ap #933-4597 Neque Rd."
    },
    {
      "country": "France",
      "name": "Sade Huffman",
      "address": "954-4199 Sed Street"
    },
    {
      "country": "United Kingdom",
      "name": "Catherine Ellison",
      "address": "801-8716 Malesuada Rd."
    },
    {
      "country": "Canada",
      "name": "Sarah Webb",
      "address": "Ap #360-1298 Mi. Street"
    },
    {
      "country": "United States",
      "name": "Moana Rivers",
      "address": "Ap #529-3483 Tempus, Street"
    },
    {
      "country": "Austria",
      "name": "Aladdin Mccullough",
      "address": "7046 Volutpat. Rd."
    },
    {
      "country": "Chile",
      "name": "Meghan Scott",
      "address": "537 Sed Ave"
    },
    {
      "country": "Canada",
      "name": "Raymond Fry",
      "address": "511-2667 Risus. St."
    },
    {
      "country": "United Kingdom",
      "name": "Seth Deleon",
      "address": "119-6726 Nulla Street"
    },
    {
      "country": "France",
      "name": "Quon Oneal",
      "address": "182-8276 Sed Road"
    },
    {
      "country": "Canada",
      "name": "Zia Mcpherson",
      "address": "143-1349 Sed St."
    },
    {
      "country": "Chile",
      "name": "Forrest Goodwin",
      "address": "274-6372 Ligula. St."
    },
    {
      "country": "France",
      "name": "Ishmael Joyce",
      "address": "Ap #747-5040 Sed Rd."
    },
    {
      "country": "Costa Rica",
      "name": "Dale Hanson",
      "address": "4356 Primis Ave"
    },
    {
      "country": "Austria",
      "name": "Oren Morris",
      "address": "P.O. Box 205, 3097 Viverra. Ave"
    },
    {
      "country": "Ireland",
      "name": "Nyssa Gordon",
      "address": "349-1614 A Rd."
    },
    {
      "country": "Sweden",
      "name": "Bianca Mcmillan",
      "address": "1881 Gravida Rd."
    },
    {
      "country": "Pakistan",
      "name": "Acton Kelley",
      "address": "Ap #211-5076 Non Ave"
    },
    {
      "country": "Colombia",
      "name": "Thomas Lee",
      "address": "905 Aptent Ave"
    },
    {
      "country": "Costa Rica",
      "name": "Stephanie Hayes",
      "address": "Ap #998-845 Vulputate Road"
    },
    {
      "country": "Vietnam",
      "name": "Plato Mcdonald",
      "address": "506-1406 Ut, Road"
    },
    {
      "country": "New Zealand",
      "name": "Amir Herring",
      "address": "120-8894 Bibendum Ave"
    },
    {
      "country": "Netherlands",
      "name": "Preston Spears",
      "address": "761-9008 Arcu Rd."
    },
    {
      "country": "Canada",
      "name": "Stacey Potts",
      "address": "Ap #163-2638 Nulla Ave"
    },
    {
      "country": "Spain",
      "name": "Oprah Patterson",
      "address": "Ap #860-4211 Erat. Ave"
    },
    {
      "country": "United States",
      "name": "Molly Stanley",
      "address": "2639 Tellus Ave"
    },
    {
      "country": "Germany",
      "name": "Melodie Foreman",
      "address": "P.O. Box 926, 8817 Ut, Ave"
    },
    {
      "country": "Ireland",
      "name": "Elliott Sykes",
      "address": "4115 At, St."
    },
    {
      "country": "Australia",
      "name": "Leroy Albert",
      "address": "3723 Eu Avenue"
    },
    {
      "country": "Mexico",
      "name": "Katelyn Booth",
      "address": "3036 Donec Av."
    },
    {
      "country": "Costa Rica",
      "name": "Aladdin Beasley",
      "address": "818-2559 Magnis Road"
    },
    {
      "country": "Costa Rica",
      "name": "Heather Castillo",
      "address": "Ap #303-5664 Erat, Street"
    },
    {
      "country": "Austria",
      "name": "Deirdre Branch",
      "address": "Ap #610-9355 Eget St."
    },
    {
      "country": "Austria",
      "name": "Edward Lee",
      "address": "Ap #236-2286 Augue Ave"
    },
    {
      "country": "Australia",
      "name": "India Acevedo",
      "address": "Ap #522-6932 Euismod Rd."
    }
  ]
}
